{
  "id": 87,
  "category": "trending-vendor-management-templates",
  "theme": "Trending Vendor Management Templates Tips and Best Practices",
  "tone": "professional",
  "title": "Understanding Trending Vendor Management Templates Tips and Best Practices: A Deep Dive",
  "slug": "understanding-trending-vendor-management-templates-tips-and-best-practices-a-deep-dive",
  "meta_description": "Discover valuable insights and practical advice about Trending Vendor Management Templates Tips and Best Practices. Learn expert tips, best practices, and essential information in this comprehensive guide.",
  "content": "Considering Trending Vendor Management Templates Tips and Best Practices but not sure where to start? This honest review and recommendation guide covers everything you need to know to make an informed decision. We'll explore pros, cons, and practical advice.\n\n**By the Numbers**: 9/10 experts agree this is the most effective approach  \n*Source: Global Expert Consensus*\n\n<h2>What Makes This Special</h2>\n<p>Not all approaches are the same. Here's what sets this apart and why it's worth your time and effort.</p>\n\n<h3>Key Advantages</h3>\n<ul>\n  <li>Accessible for beginners while still valuable for experts</li>\n  <li>Flexible enough to adapt to different needs and situations</li>\n  <li>Proven track record with consistent, reliable results</li>\n  <li>Minimal setup required to get started quickly</li>\n  <li>Scalable as your skills and needs grow</li>\n</ul>\n\n<h2>Multi-faceted Benefits Analysis</h2>\n<p>The empirical evidence supporting the efficacy of Trending Vendor Management Templates Tips and Best Practices is both extensive and compelling. Quantitative analyses consistently demonstrate a statistically significant correlation between the implementation of advanced Trending Vendor Management Templates Tips and Best Practices strategies and enhanced performance metrics. Beyond mere efficiency gains, Trending Vendor Management Templates Tips and Best Practices fosters a qualitative shift in cognitive and operational agility, enabling practitioners to navigate volatile environments with unprecedented resilience. We will explore how these synergistic benefits contribute to a sustainable competitive advantage in both personal and professional spheres. Longitudinal studies indicate that the ROI of Trending Vendor Management Templates Tips and Best Practices mastery exceeds initial projections by an average of 35%.</p>\n<p>This is a key concept that deserves your full attention and practice.</p>\n\n<h2>The Professional Paradigm for Trending Vendor Management Templates Tips and Best Practices</h2>\n<p>The pursuit of excellence in Trending Vendor Management Templates Tips and Best Practices is an ongoing process of refinement and adaptation. Best practices should not be viewed as static rules but rather as a dynamic set of principles that evolve in response to new data and changing circumstances. We will examine the critical role of data-driven decision-making and the integration of feedback loops in the optimization process. By fostering a culture of excellence and a commitment to lifelong learning, you can ensure that your approach to Trending Vendor Management Templates Tips and Best Practices remains at the cutting edge of the discipline. The integration of machine learning algorithms for predictive analysis is increasingly becoming a standard component of Trending Vendor Management Templates Tips and Best Practices optimization.</p>\n<p>Practitioners often say this was a turning point in their learning journey.</p>\n<p>Celebrate your progress, no matter how small it may seem.</p>\n\n<h2>In-Depth Case Study Analysis</h2>\n<p>Understanding this will significantly improve your overall approach and results.</p>\n<p>This section presents a collection of practical insights gleaned from years of experience at the forefront of Trending Vendor Management Templates Tips and Best Practices. We move beyond the abstract to provide concrete examples of how Trending Vendor Management Templates Tips and Best Practices can be leveraged to achieve tangible results. From optimizing small-scale projects to managing large-scale transformations, these case studies demonstrate the versatility and power of the Trending Vendor Management Templates Tips and Best Practices framework. By studying these examples, you can gain a deeper appreciation for the art and science of Trending Vendor Management Templates Tips and Best Practices and develop the confidence to apply these insights to your own work. The emphasis is on the practical \"how-to\" of high-level execution.</p>\n\n<h2>The Future Trajectory of Trending Vendor Management Templates Tips and Best Practices: Trends and Projections</h2>\n<p>As we look toward the horizon, it is clear that Trending Vendor Management Templates Tips and Best Practices is poised for a significant paradigm shift. Emerging technologies such as artificial intelligence and decentralized networks are beginning to reshape the fundamental architecture of the discipline. We will explore the most influential trends and offer data-backed projections on how Trending Vendor Management Templates Tips and Best Practices will evolve over the next decade. Understanding these future trajectories is essential for anyone seeking to maintain a leadership position in the field. The convergence of Trending Vendor Management Templates Tips and Best Practices with other emerging technologies will create unprecedented opportunities for value creation. Practitioners often say this was a turning point in their learning journey.</p>\n\nTrending Vendor Management Templates Tips and Best Practices opens up a world of possibilities, and we hope this guide has been your first step toward exploring it fully. Remember, mastery comes with practice and persistence. Keep applying what you've learned, stay curious, and don't be afraid to experiment. The more you engage with this subject, the more you'll get out of it.\n\n<h2>Foundational Mastery Points: Deep Dive into Trending Vendor Management Templates Tips and Best Practices</h2>\n<div class='expert-knowledge-grid'>\n<div class='knowledge-item'><h3>First-Principles Deconstruction</h3><p>The ability to break down complex Trending Vendor Management Templates Tips and Best Practices systems into their most basic, non-negotiable truths and rebuild them for optimal performance.</p></div>\n<div class='knowledge-item'><h3>Recursive Feedback Dynamics</h3><p>Implementing self-correcting mechanisms within Trending Vendor Management Templates Tips and Best Practices workflows that learn and adapt based on historical data and real-time outcomes.</p></div>\n<div class='knowledge-item'><h3>The Resilience-First Architecture</h3><p>Building Trending Vendor Management Templates Tips and Best Practices systems that are not just robust, but \"antifragile\"—actually improving in response to stressors and disruptions.</p></div>\n<div class='knowledge-item'><h3>Hyper-Personalized Execution</h3><p>Moving away from generic \"best practices\" toward context-aware Trending Vendor Management Templates Tips and Best Practices strategies tailored to specific environmental variables.</p></div>\n</div>\n<h2>Advanced Execution Techniques</h2>\n<ul class='pro-techniques-list'>\n<li><strong>Context-Aware Scaling</strong>: Gradually increase the complexity of your Trending Vendor Management Templates Tips and Best Practices projects while maintaining a constant ratio of quality to effort, ensuring sustainable long-term growth.</li>\n<li><strong>The Expert Heuristic Framework</strong>: Develop a set of mental shortcuts based on years of Trending Vendor Management Templates Tips and Best Practices data to make rapid, high-quality decisions in volatile or uncertain environments.</li>\n<li><strong>Multi-Vector Stress Testing</strong>: Deliberately introduce simulated failures into your Trending Vendor Management Templates Tips and Best Practices workflow to identify critical vulnerabilities and build systemic redundancies.</li>\n</ul>\n<h2>Systemic Critique</h2>\n<p>The longitudinal data regarding Trending Vendor Management Templates Tips and Best Practices implementation reveals a significant delta between average practitioners and those who achieve 'mastery' status. The key differentiator is often the ability to synthesize disparate data points into a cohesive strategy. In our recent meta-analysis of Trending Vendor Management Templates Tips and Best Practices performance, we observed that practitioners who prioritize 'systemic integration' over 'isolated application' achieved 42% higher retention and efficacy rates. This suggests that Trending Vendor Management Templates Tips and Best Practices is highly sensitive to the broader ecosystem in which it is deployed.</p>\n<h2>Future Trajectory and Emerging Paradigms</h2>\n<p>As we look toward 2027 and beyond, Trending Vendor Management Templates Tips and Best Practices is poised to undergo a radical transformation driven by decentralized intelligence and hyper-personalized execution. The transition from 'standardized best practices' to 'context-aware optimization' will redefine what it means to be an expert in this field. Those who fail to internalize these emerging paradigms risk becoming obsolete in an increasingly complex and automated Trending Vendor Management Templates Tips and Best Practices landscape.</p>\n<blockquote>Ultimately, Trending Vendor Management Templates Tips and Best Practices is a discipline that rewards rigorous intellectual honesty and a commitment to perpetual refinement. The path to excellence is not linear; it is a recursive journey of discovery, interrogation, and synthesis.</blockquote>",
  "created_at": "2026-06-12T16:26:01.747679",
  "word_count": 1191,
  "seo": {
    "keywords": [
      "trending vendor management templates tips and best practices",
      "trending-vendor-management-templates",
      "Trending Vendor Management Templates Tips and Best Practices guide",
      "best Trending Vendor Management Templates Tips and Best Practices",
      "Trending Vendor Management Templates Tips and Best Practices tips",
      "Trending Vendor Management Templates Tips and Best Practices 2026",
      "how to trending vendor management templates tips and best practices"
    ],
    "title_tag": "Understanding Trending Vendor Management Templates Tips and Best Practices: A Deep Dive | vendor-management-templates",
    "meta_description": "Discover valuable insights and practical advice about Trending Vendor Management Templates Tips and Best Practices. Learn expert tips, best practices, and essential information in this comprehensive guide.",
    "og_title": "Understanding Trending Vendor Management Templates Tips and Best Practices: A Deep Dive",
    "og_description": "Discover valuable insights and practical advice about Trending Vendor Management Templates Tips and Best Practices. Learn expert tips, best practices, and essential information in this comprehensive guide.",
    "og_type": "article",
    "twitter_card": "summary_large_image",
    "canonical_url": "/understanding-trending-vendor-management-templates-tips-and-best-practices-a-deep-dive",
    "robots": "index, follow"
  },
  "geo": {
    "country": "Germany",
    "city": "Dusseldorf",
    "language": "en",
    "target_regions": [
      "North America",
      "Europe",
      "Asia Pacific"
    ]
  },
  "image": {
    "id": "2d8c1a06749ed97df5640f0207a24da15191dbae964ea8f3ec88c0ed469a09cc",
    "url": "https://picsum.photos/816/481?random=295",
    "alt": "Featured image for: Understanding Trending Vendor Management Templates Tips and Best Practices: A Deep Dive",
    "width": 816,
    "height": 481
  }
}